epage-1.0.0.data/scripts/SVM_ROC.py
epage-1.0.0.data/scripts/SVM_performance.py
epage-1.0.0.data/scripts/SVM_predict.py
epage-1.0.0.data/scripts/gComposite.py
pacmodule/__init__.py
pacmodule/cpca.py
pacmodule/gsva.py
pacmodule/iList.py
pacmodule/iMatrix.py
pacmodule/iPas.py
pacmodule/iReader.py
pacmodule/svm.py
epage-1.0.0.dist-info/LICENSE.txt
epage-1.0.0.dist-info/METADATA
epage-1.0.0.dist-info/WHEEL
epage-1.0.0.dist-info/top_level.txt
epage-1.0.0.dist-info/RECORD
