Metadata-Version: 2.1
Name: epage
Version: 1.0.0
Summary: Evaluate Protein Activity with Gene Expression
Home-page: https://camp.readthedocs.io/en/latest/index.html
Author: Liguo Wang
Author-email: wangliguo78@gmail.com
License: UNKNOWN
Keywords: Somatic mutation,gain of function,loss of function,protein activity,composite expression score
Platform: Linux
Platform: MacOS
Classifier: Development Status :: 5 - Production/Stable
Classifier: Environment :: Console
Classifier: Intended Audience :: Science/Research
Classifier: License :: OSI Approved :: GNU General Public License v2 (GPLv2)
Classifier: Operating System :: MacOS :: MacOS X
Classifier: Operating System :: POSIX
Classifier: Programming Language :: Python
Classifier: Topic :: Scientific/Engineering :: Bio-Informatics
Requires-Python: >=3.5
Requires-Dist: numpy
Requires-Dist: scipy
Requires-Dist: sklearn
Requires-Dist: pandas
